wdadaptivepy/__init__.py
wdadaptivepy/connectors/__init__.py
wdadaptivepy/connectors/xml_api/__init__.py
wdadaptivepy/connectors/xml_api/constants.py
wdadaptivepy/connectors/xml_api/exceptions.py
wdadaptivepy/connectors/xml_api/xml_api.py
wdadaptivepy/main.py
wdadaptivepy/models/__init__.py
wdadaptivepy/models/account.py
wdadaptivepy/models/attribute.py
wdadaptivepy/models/attribute_value.py
wdadaptivepy/models/base.py
wdadaptivepy/models/currency.py
wdadaptivepy/models/data.py
wdadaptivepy/models/dimension.py
wdadaptivepy/models/dimension_value.py
wdadaptivepy/models/exceptions.py
wdadaptivepy/models/group.py
wdadaptivepy/models/level.py
wdadaptivepy/models/list.py
wdadaptivepy/models/permission_set.py
wdadaptivepy/models/time.py
wdadaptivepy/models/user.py
wdadaptivepy/models/version.py
wdadaptivepy/py.typed
wdadaptivepy/services/__init__.py
wdadaptivepy/services/accounts.py
wdadaptivepy/services/attribute_values.py
wdadaptivepy/services/attributes.py
wdadaptivepy/services/currencies.py
wdadaptivepy/services/data.py
wdadaptivepy/services/dimension_values.py
wdadaptivepy/services/dimensions.py
wdadaptivepy/services/groups.py
wdadaptivepy/services/levels.py
wdadaptivepy/services/permission_sets.py
wdadaptivepy/services/time.py
wdadaptivepy/services/users.py
wdadaptivepy/services/versions.py
wdadaptivepy-0.1.0.dist-info/WHEEL
wdadaptivepy-0.1.0.dist-info/METADATA
wdadaptivepy-0.1.0.dist-info/RECORD
