Metadata-Version: 2.3
Name: wdadaptivepy
Version: 0.1.0
Summary: Wrapper for Workday Adaptive Planning's API
Keywords: Adaptive Insights,Adaptive Planning,Workday,Workday Adaptive Planning,api wrapper,financial planning,business analytics
Author: Revelwood Labs
Author-email: Revelwood Labs <labs@revelwood.com>
License:                     GNU GENERAL PUBLIC LICENSE
Classifier: Development Status :: 4 - Beta
Classifier: Intended Audience :: Developers
Classifier: Intended Audience :: System Administrators
Classifier: Intended Audience :: Financial and Insurance Industry
Classifier: License :: OSI Approved :: GNU General Public License v3 (GPLv3)
Classifier: Natural Language :: English
Classifier: Operating System :: OS Independent
Classifier: Programming Language :: Python :: 3.12
Classifier: Topic :: Office/Business :: Financial
Requires-Dist: requests>=2.32.4
Maintainer: Revelwood Labs
Maintainer-email: Revelwood Labs <labs@revelwood.com>
Requires-Python: >=3.12
Project-URL: Bug Tracker, https://github.com/revelwood/wdadaptivepy/issues
Project-URL: Documentation, https://revelwood.github.io/wdadaptivepy
Project-URL: Homepage, https://revelwood.github.io/wdadaptivepy
Project-URL: Repository, https://github.com/revelwood/wdadaptivepy
